exterminator.py
exterminator-0.8.dist-info/LICENSE
exterminator-0.8.dist-info/METADATA
exterminator-0.8.dist-info/WHEEL
exterminator-0.8.dist-info/top_level.txt
exterminator-0.8.dist-info/RECORD
