Metadata-Version: 2.1
Name: exterminator
Version: 0.8
Summary: Log the important data when a exception occurs.
Home-page: https://github.com/dermasmid/python-exterminator
Author: Cheskel Twersky
Author-email: yoursn21@gmail.com
License: MIT
Platform: UNKNOWN
Classifier: Programming Language :: Python :: 3
Classifier: License :: OSI Approved :: MIT License
Classifier: Operating System :: OS Independent
Requires-Python: >=3.6
